{"water-areas":{"features":[],"type":"FeatureCollection"},"highroad":{"features":[{"clipped":true,"geometry":{"coordinates":[[97.042895,20.673905],[97.042741,20.674196],[97.042741,20.674999],[97.042902,20.677438],[97.040478,20.686648],[97.040532,20.687461],[97.041185,20.688409],[97.043567,20.690948],[97.045065,20.694462]],"type":"LineString"},"type":"Feature","id":"230941476","properties":{"kind":"rail","is_link":"no","is_bridge":"no","railway":"rail","sort_key":-7,"is_tunnel":"no","highway":null}}],"type":"FeatureCollection"}}
