{"water-areas":{"features":[{"clipped":true,"geometry":{"coordinates":[[[96.913153,20.509354],[96.908942,20.512755],[96.908934,20.518126],[96.902139,20.519725],[96.901477,20.52033],[96.901315,20.521205],[96.900876,20.521709],[96.89941,20.522532],[96.89941,20.529932],[96.921383,20.529932],[96.921383,20.509354],[96.913153,20.509354]]],"type":"Polygon"},"type":"Feature","id":"24058885","properties":{"source":"openstreetmap.org","kind":"water","area":55058906,"name":"အင်းလေးကန်"}}],"type":"FeatureCollection"},"highroad":{"features":[],"type":"FeatureCollection"}}
