{"water-areas":{"features":[],"type":"FeatureCollection"},"highroad":{"features":[{"clipped":true,"geometry":{"coordinates":[[94.965822,21.331222],[94.966549,21.331512],[94.971699,21.331193],[94.974845,21.330745],[94.975755,21.330693],[94.976457,21.3308],[94.978487,21.331566],[94.987795,21.336228]],"type":"LineString"},"type":"Feature","id":"267093356","properties":{"kind":"rail","is_link":"no","is_bridge":"no","railway":"rail","sort_key":-7,"is_tunnel":"no","highway":null}},{"clipped":true,"geometry":{"coordinates":[[94.980199,21.332417],[94.978025,21.33136]],"type":"LineString"},"type":"Feature","id":"199132360","properties":{"kind":"rail","is_link":"no","is_bridge":"no","railway":"rail","sort_key":-7,"is_tunnel":"no","highway":null}},{"clipped":true,"geometry":{"coordinates":[[94.979619,21.330315],[94.979023,21.33152],[94.978792,21.331555]],"type":"LineString"},"type":"Feature","id":"199132409","properties":{"kind":"minor_road","is_link":"no","is_bridge":"no","railway":null,"sort_key":-6,"is_tunnel":"no","highway":"residential"}},{"clipped":true,"geometry":{"coordinates":[[94.976358,21.330315],[94.97503,21.330586],[94.974521,21.331054],[94.973584,21.331406],[94.972763,21.331466],[94.970191,21.332839],[94.965822,21.33477]],"type":"LineString"},"type":"Feature","id":"187056528","properties":{"kind":"major_road","is_link":"no","is_bridge":"no","railway":null,"sort_key":-2,"is_tunnel":"no","highway":"primary"}}],"type":"FeatureCollection"}}
