{"water-areas":{"features":[],"type":"FeatureCollection"},"highroad":{"features":[{"clipped":true,"geometry":{"coordinates":[[96.701664,20.927107],[96.699909,20.927634],[96.698962,20.92806],[96.69537,20.930023],[96.692345,20.931396],[96.690843,20.933008],[96.688537,20.933953],[96.684481,20.936218],[96.679691,20.937587]],"type":"LineString"},"type":"Feature","id":"103423208","properties":{"kind":"major_road","is_link":"no","is_bridge":"no","railway":null,"sort_key":-4,"is_tunnel":"no","highway":"tertiary"}}],"type":"FeatureCollection"}}
