{"water-areas":{"features":[{"clipped":true,"geometry":{"coordinates":[[[94.857507,21.176728],[94.856365,21.175428],[94.855959,21.174816],[94.855959,21.176728],[94.857507,21.176728]]],"type":"Polygon"},"type":"Feature","id":"aca9aead7f","properties":{"source":"openstreetmap.org","kind":"riverbank","area":51185237,"name":null}}],"type":"FeatureCollection"},"highroad":{"features":[{"clipped":true,"geometry":{"coordinates":[[94.864834,21.17222],[94.865264,21.172379],[94.865447,21.172554],[94.866108,21.173505],[94.866945,21.174242]],"type":"LineString"},"type":"Feature","id":"46715095","properties":{"kind":"major_road","is_link":"no","is_bridge":"no","railway":null,"sort_key":-3,"is_tunnel":"no","highway":"secondary"}},{"clipped":true,"geometry":{"coordinates":[[94.855959,21.168875],[94.856583,21.16911],[94.857941,21.169821],[94.858053,21.169949]],"type":"LineString"},"type":"Feature","id":"23395198","properties":{"kind":"minor_road","is_link":"no","is_bridge":"no","railway":null,"sort_key":-6,"is_tunnel":"no","highway":"unclassified"}},{"clipped":true,"geometry":{"coordinates":[[94.860738,21.172105],[94.861004,21.173336],[94.861027,21.173741],[94.860988,21.174953],[94.86082,21.176728]],"type":"LineString"},"type":"Feature","id":"23395368","properties":{"kind":"minor_road","is_link":"no","is_bridge":"no","railway":null,"sort_key":-6,"is_tunnel":"no","highway":"unclassified"}},{"clipped":true,"geometry":{"coordinates":[[94.860988,21.174953],[94.861644,21.17499],[94.862611,21.174925],[94.864226,21.175286],[94.864524,21.175444]],"type":"LineString"},"type":"Feature","id":"101983670","properties":{"kind":"path","is_link":"no","is_bridge":"no","railway":null,"sort_key":-9,"is_tunnel":"no","highway":"path"}},{"clipped":true,"geometry":{"coordinates":[[94.858566,21.171855],[94.858415,21.171968],[94.858423,21.172721],[94.858063,21.17519],[94.858027,21.175911]],"type":"LineString"},"type":"Feature","id":"46711016","properties":{"kind":"minor_road","is_link":"no","is_bridge":"no","railway":null,"sort_key":-6,"is_tunnel":"no","highway":"residential"}},{"clipped":true,"geometry":{"coordinates":[[94.858423,21.172721],[94.85888,21.172747],[94.859159,21.172833],[94.860908,21.1729]],"type":"LineString"},"type":"Feature","id":"199122447","properties":{"kind":"minor_road","is_link":"no","is_bridge":"no","railway":null,"sort_key":-6,"is_tunnel":"no","highway":"residential"}},{"clipped":true,"geometry":{"coordinates":[[94.862534,21.172156],[94.862604,21.170802],[94.862672,21.170551],[94.863465,21.169502],[94.863591,21.169243]],"type":"LineString"},"type":"Feature","id":"23395205","properties":{"kind":"minor_road","is_link":"no","is_bridge":"no","railway":null,"sort_key":-6,"is_tunnel":"no","highway":"residential"}},{"clipped":true,"geometry":{"coordinates":[[94.866945,21.168081],[94.863361,21.166483]],"type":"LineString"},"type":"Feature","id":"46711010","properties":{"kind":"major_road","is_link":"no","is_bridge":"no","railway":null,"sort_key":-3,"is_tunnel":"no","highway":"secondary"}},{"clipped":true,"geometry":{"coordinates":[[94.863544,21.166483],[94.866945,21.168006]],"type":"LineString"},"type":"Feature","id":"237941121","properties":{"kind":"major_road","is_link":"no","is_bridge":"no","railway":null,"sort_key":-3,"is_tunnel":"no","highway":"secondary"}},{"clipped":true,"geometry":{"coordinates":[[94.865763,21.173009],[94.865715,21.173211],[94.865514,21.173534],[94.865786,21.173963]],"type":"LineString"},"type":"Feature","id":"236319542","properties":{"kind":"minor_road","is_link":"no","is_bridge":"no","railway":null,"sort_key":-7,"is_tunnel":"no","highway":"service"}},{"clipped":true,"geometry":{"coordinates":[[94.865802,21.167495],[94.865769,21.167554]],"type":"LineString"},"type":"Feature","id":"286122344","properties":{"kind":"minor_road","is_link":"no","is_bridge":"no","railway":null,"sort_key":-6,"is_tunnel":"no","highway":"unclassified"}},{"clipped":true,"geometry":{"coordinates":[[94.865406,21.167392],[94.865769,21.167554],[94.866164,21.168872]],"type":"LineString"},"type":"Feature","id":"145114678","properties":{"kind":"path","is_link":"no","is_bridge":"no","railway":null,"sort_key":-9,"is_tunnel":"no","highway":"track"}},{"clipped":true,"geometry":{"coordinates":[[94.865377,21.166483],[94.865406,21.167392]],"type":"LineString"},"type":"Feature","id":"161777480","properties":{"kind":"minor_road","is_link":"no","is_bridge":"no","railway":null,"sort_key":-6,"is_tunnel":"no","highway":"unclassified"}},{"clipped":true,"geometry":{"coordinates":[[94.863337,21.166483],[94.863096,21.167954],[94.863285,21.168351],[94.863519,21.168636],[94.863526,21.169011]],"type":"LineString"},"type":"Feature","id":"80179256","properties":{"kind":"minor_road","is_link":"no","is_bridge":"no","railway":null,"sort_key":-6,"is_tunnel":"no","highway":"unclassified"}},{"clipped":true,"geometry":{"coordinates":[[94.85804,21.175437],[94.860191,21.175496],[94.860947,21.175417]],"type":"LineString"},"type":"Feature","id":"101983672","properties":{"kind":"minor_road","is_link":"no","is_bridge":"no","railway":null,"sort_key":-6,"is_tunnel":"no","highway":"residential"}},{"clipped":true,"geometry":{"coordinates":[[94.858277,21.176444],[94.857968,21.176728]],"type":"LineString"},"type":"Feature","id":"161764106","properties":{"kind":"path","is_link":"no","is_bridge":"no","railway":null,"sort_key":-9,"is_tunnel":"no","highway":"steps"}},{"clipped":true,"geometry":{"coordinates":[[94.858415,21.171968],[94.858409,21.171666]],"type":"LineString"},"type":"Feature","id":"101983668","properties":{"kind":"minor_road","is_link":"no","is_bridge":"no","railway":null,"sort_key":-6,"is_tunnel":"no","highway":"unclassified"}},{"clipped":true,"geometry":{"coordinates":[[94.863102,21.169973],[94.862669,21.169958],[94.861969,21.169759],[94.861745,21.169602],[94.85976,21.169169],[94.859129,21.168922],[94.858268,21.168781],[94.857837,21.16854]],"type":"LineString"},"type":"Feature","id":"164457956","properties":{"kind":"path","is_link":"no","is_bridge":"no","railway":null,"sort_key":-9,"is_tunnel":"no","highway":"track"}},{"clipped":true,"geometry":{"coordinates":[[94.866108,21.173505],[94.865936,21.173838],[94.865656,21.17411],[94.865483,21.174475],[94.865108,21.176116],[94.865104,21.17627],[94.865299,21.176602],[94.865269,21.176728]],"type":"LineString"},"type":"Feature","id":"101983662","properties":{"kind":"minor_road","is_link":"no","is_bridge":"no","railway":null,"sort_key":-6,"is_tunnel":"no","highway":"residential"}},{"clipped":true,"geometry":{"coordinates":[[94.859111,21.166483],[94.859111,21.166755],[94.859047,21.166851],[94.858897,21.166888],[94.858612,21.166783],[94.858243,21.166483]],"type":"LineString"},"type":"Feature","id":"101989052","properties":{"kind":"minor_road","is_link":"no","is_bridge":"no","railway":null,"sort_key":-6,"is_tunnel":"no","highway":"residential"}},{"clipped":true,"geometry":{"coordinates":[[94.866945,21.176012],[94.865226,21.17554]],"type":"LineString"},"type":"Feature","id":"203220116","properties":{"kind":"minor_road","is_link":"no","is_bridge":"no","railway":null,"sort_key":-6,"is_tunnel":"no","highway":"residential"}},{"clipped":true,"geometry":{"coordinates":[[94.862265,21.175267],[94.862382,21.175195],[94.862479,21.174924]],"type":"LineString"},"type":"Feature","id":"101983661","properties":{"kind":"path","is_link":"no","is_bridge":"no","railway":null,"sort_key":-9,"is_tunnel":"no","highway":"path"}},{"clipped":true,"geometry":{"coordinates":[[94.863884,21.175202],[94.86391,21.17506]],"type":"LineString"},"type":"Feature","id":"101983669","properties":{"kind":"path","is_link":"no","is_bridge":"no","railway":null,"sort_key":-9,"is_tunnel":"no","highway":"path"}},{"clipped":true,"geometry":{"coordinates":[[94.864492,21.175631],[94.865156,21.175771]],"type":"LineString"},"type":"Feature","id":"101983665","properties":{"kind":"minor_road","is_link":"no","is_bridge":"no","railway":null,"sort_key":-6,"is_tunnel":"no","highway":"residential"}},{"clipped":true,"geometry":{"coordinates":[[94.864872,21.175711],[94.864914,21.176036],[94.865236,21.176578],[94.865217,21.176728]],"type":"LineString"},"type":"Feature","id":"162009362","properties":{"kind":"path","is_link":"no","is_bridge":"no","railway":null,"sort_key":-9,"is_tunnel":"no","highway":"track"}},{"clipped":true,"geometry":{"coordinates":[[94.865157,21.176436],[94.865039,21.176442],[94.865033,21.176524],[94.865187,21.176728]],"type":"LineString"},"type":"Feature","id":"162009372","properties":{"kind":"path","is_link":"no","is_bridge":"no","railway":null,"sort_key":-9,"is_tunnel":"no","highway":"track"}},{"clipped":true,"geometry":{"coordinates":[[94.857654,21.167259],[94.858053,21.169949]],"type":"LineString"},"type":"Feature","id":"46715103","properties":{"kind":"major_road","is_link":"no","is_bridge":"no","railway":null,"sort_key":-3,"is_tunnel":"no","highway":"secondary"}},{"clipped":true,"geometry":{"coordinates":[[94.858053,21.169949],[94.858348,21.171496],[94.858485,21.171792],[94.858675,21.1719],[94.861629,21.172165],[94.863748,21.172116],[94.864834,21.17222]],"type":"LineString"},"type":"Feature","id":"101983659","properties":{"kind":"major_road","is_link":"no","is_bridge":"no","railway":null,"sort_key":-3,"is_tunnel":"no","highway":"secondary"}},{"clipped":true,"geometry":{"coordinates":[[94.857798,21.166483],[94.857654,21.167259]],"type":"LineString"},"type":"Feature","id":"237941119","properties":{"kind":"major_road","is_link":"no","is_bridge":"no","railway":null,"sort_key":-3,"is_tunnel":"no","highway":"secondary"}},{"clipped":true,"geometry":{"coordinates":[[94.857654,21.167259],[94.857721,21.166483]],"type":"LineString"},"type":"Feature","id":"237941193","properties":{"kind":"major_road","is_link":"no","is_bridge":"no","railway":null,"sort_key":-3,"is_tunnel":"no","highway":"secondary"}},{"clipped":true,"geometry":{"coordinates":[[94.865447,21.172554],[94.865498,21.17215],[94.866528,21.170536],[94.866945,21.169994]],"type":"LineString"},"type":"Feature","id":"80178229","properties":{"kind":"minor_road","is_link":"no","is_bridge":"no","railway":null,"sort_key":-6,"is_tunnel":"no","highway":"unclassified"}},{"clipped":true,"geometry":{"coordinates":[[94.865498,21.17215],[94.866945,21.172618]],"type":"LineString"},"type":"Feature","id":"23395212","properties":{"kind":"minor_road","is_link":"no","is_bridge":"no","railway":null,"sort_key":-6,"is_tunnel":"no","highway":"unclassified"}},{"clipped":true,"geometry":{"coordinates":[[94.863748,21.172116],[94.863806,21.170984],[94.863712,21.170189],[94.863595,21.169883],[94.863622,21.169418],[94.863526,21.169011]],"type":"LineString"},"type":"Feature","id":"101989149","properties":{"kind":"minor_road","is_link":"no","is_bridge":"no","railway":null,"sort_key":-6,"is_tunnel":"no","highway":"residential"}},{"clipped":true,"geometry":{"coordinates":[[94.866528,21.170536],[94.866131,21.17037],[94.865327,21.170218],[94.864843,21.170045],[94.864306,21.170108],[94.863675,21.170088],[94.863102,21.169973]],"type":"LineString"},"type":"Feature","id":"268279059","properties":{"kind":"minor_road","is_link":"no","is_bridge":"no","railway":null,"sort_key":-6,"is_tunnel":"no","highway":"unclassified"}},{"clipped":true,"geometry":{"coordinates":[[94.866945,21.17069],[94.866528,21.170536]],"type":"LineString"},"type":"Feature","id":"23395204","properties":{"kind":"path","is_link":"no","is_bridge":"no","railway":null,"sort_key":-9,"is_tunnel":"no","highway":"footway"}},{"clipped":true,"geometry":{"coordinates":[[94.862082,21.16873],[94.861651,21.168718],[94.860488,21.168505],[94.860237,21.168577],[94.859703,21.168544],[94.85941,21.168412],[94.857783,21.168124]],"type":"LineString"},"type":"Feature","id":"199122429","properties":{"kind":"path","is_link":"no","is_bridge":"no","railway":null,"sort_key":-9,"is_tunnel":"no","highway":"track"}},{"clipped":true,"geometry":{"coordinates":[[94.858601,21.168845],[94.858231,21.169014],[94.857956,21.169254]],"type":"LineString"},"type":"Feature","id":"101983654","properties":{"kind":"path","is_link":"no","is_bridge":"no","railway":null,"sort_key":-9,"is_tunnel":"no","highway":"track"}},{"clipped":true,"geometry":{"coordinates":[[94.857956,21.169254],[94.857731,21.169566],[94.857536,21.169614]],"type":"LineString"},"type":"Feature","id":"233630220","properties":{"kind":"minor_road","is_link":"no","is_bridge":"no","railway":null,"sort_key":-6,"is_tunnel":"no","highway":"unclassified"}},{"clipped":true,"geometry":{"coordinates":[[94.865873,21.170311],[94.86622,21.169588],[94.866164,21.168872]],"type":"LineString"},"type":"Feature","id":"23395207","properties":{"kind":"minor_road","is_link":"no","is_bridge":"no","railway":null,"sort_key":-6,"is_tunnel":"no","highway":"unclassified"}},{"clipped":true,"geometry":{"coordinates":[[94.863424,21.168816],[94.863556,21.168822]],"type":"LineString"},"type":"Feature","id":"101989051","properties":{"kind":"path","is_link":"no","is_bridge":"no","railway":null,"sort_key":-9,"is_tunnel":"no","highway":"footway"}},{"clipped":true,"geometry":{"coordinates":[[94.864014,21.176728],[94.864459,21.175791],[94.864989,21.172259]],"type":"LineString"},"type":"Feature","id":"101989125","properties":{"kind":"minor_road","is_link":"no","is_bridge":"no","railway":null,"sort_key":-6,"is_tunnel":"no","highway":"residential"}},{"clipped":true,"geometry":{"coordinates":[[94.866925,21.168071],[94.866945,21.168045]],"type":"LineString"},"type":"Feature","id":"148361266","properties":{"kind":"path","is_link":"no","is_bridge":"no","railway":null,"sort_key":-9,"is_tunnel":"no","highway":"track"}},{"clipped":true,"geometry":{"coordinates":[[94.862082,21.16873],[94.862402,21.168774],[94.862539,21.16909],[94.862835,21.169269],[94.862867,21.169895],[94.863102,21.169973]],"type":"LineString"},"type":"Feature","id":"23395374","properties":{"kind":"minor_road","is_link":"no","is_bridge":"no","railway":null,"sort_key":-6,"is_tunnel":"no","highway":"unclassified"}},{"clipped":true,"geometry":{"coordinates":[[94.863526,21.169011],[94.863268,21.169162],[94.86293,21.169256],[94.862879,21.169372]],"type":"LineString"},"type":"Feature","id":"164458020","properties":{"kind":"minor_road","is_link":"no","is_bridge":"no","railway":null,"sort_key":-6,"is_tunnel":"no","highway":"unclassified"}},{"clipped":true,"geometry":{"coordinates":[[94.863167,21.168104],[94.862617,21.168364],[94.862402,21.168774]],"type":"LineString"},"type":"Feature","id":"199122445","properties":{"kind":"path","is_link":"no","is_bridge":"no","railway":null,"sort_key":-9,"is_tunnel":"no","highway":"track"}}],"type":"FeatureCollection"}}
